setup.py
jira_clt/__init__.py
jira_clt/efforts.py
jira_clt/jira_clt_base.py
jira_clt/jira_clt_efforts.py
jira_clt/logger.py
jira_clt.egg-info/PKG-INFO
jira_clt.egg-info/SOURCES.txt
jira_clt.egg-info/dependency_links.txt
jira_clt.egg-info/entry_points.txt
jira_clt.egg-info/requires.txt
jira_clt.egg-info/top_level.txt