Metadata-Version: 1.1
Name: jira-clt
Version: 1.2
Summary: Linaro JIRA Command line tools
Home-page: https://github.com/amrohassaan/jira_clt
Author: Linaro.org
Author-email: amro.hassaan@linaro.org
License: UNKNOWN
Download-URL: https://github.com/amrohassaan/jira_clt/tarball/1.2
Platform: UNKNOWN
